webcam_filters/__init__.py
webcam_filters/__main__.py
webcam_filters/click.py
webcam_filters/gst.py
webcam_filters/main.py
webcam_filters/mediapipe.py
webcam_filters/plugins/python/cv2_boxfilter.py
webcam_filters/plugins/python/numpy_where.py
webcam_filters/plugins/python/selfie_segmentation.py
webcam_filters-0.3.0.dist-info/entry_points.txt
webcam_filters-0.3.0.dist-info/LICENSE
webcam_filters-0.3.0.dist-info/WHEEL
webcam_filters-0.3.0.dist-info/METADATA
webcam_filters-0.3.0.dist-info/RECORD
