Metadata-Version: 2.1
Name: webcam-filters
Version: 0.3.0
Summary: Add filters (background blur, etc) to your webcam on Linux
Home-page: https://github.com/jashandeep-sohi/webcam-filters
License: GPL-3.0-only
Keywords: webcam,filters,v4l2,video-conferencing
Author: Jashandeep Sohi
Author-email: jashandeep.s.sohi@gmail.com
Requires-Python: >=3.8,<3.10
Classifier: License :: OSI Approved :: GNU General Public License v3 (GPLv3)
Classifier: Programming Language :: Python :: 3
Classifier: Programming Language :: Python :: 3.8
Classifier: Programming Language :: Python :: 3.9
Requires-Dist: click (>=8.0.1,<9.0.0)
Requires-Dist: click-completion (>=0.5.2,<0.6.0)
Requires-Dist: importlib-metadata (>=1.0); python_version < "3.8"
Requires-Dist: mediapipe (>=0.8.6,<0.9.0)
Requires-Dist: numpy (>=1.21.2,<2.0.0)
Requires-Dist: opencv-contrib-python (>=4.5.3,<5.0.0)
Requires-Dist: rich (>=10.7.0,<11.0.0)
Project-URL: Repository, https://github.com/jashandeep-sohi/webcam-filters
